Metadata-Version: 2.1
Name: gorpy
Version: 2.0.4
Summary: Grep tool with extensions for reading files in many different ways
Home-page: https://github.com/molsonkiko/gorpy
Author: Mark Johnston Olson
Author-email: mjolsonsfca@gmail.com
License: MIT/X
Keywords: grep tool,text mining,jsonpath
Classifier: Programming Language :: Python
Classifier: Programming Language :: Python :: 3.6
Classifier: Programming Language :: Python :: 3.7
Classifier: Programming Language :: Python :: 3.8
Classifier: Programming Language :: Python :: 3.9
Classifier: Programming Language :: Python :: 3.10
Classifier: Programming Language :: Python :: 3 :: Only
Classifier: Development Status :: 5 - Production/Stable
Classifier: Environment :: Console
Classifier: Intended Audience :: Developers
Classifier: Intended Audience :: Science/Research
Classifier: License :: OSI Approved :: MIT License
Classifier: Topic :: Text Processing
Requires-Python: >=3.6
License-File: LICENSE
Requires-Dist: math-eval
Requires-Dist: python-dateutil
Provides-Extra: docs
Requires-Dist: sphinx ; extra == 'docs'
Requires-Dist: sphinx-argparse ; extra == 'docs'
Provides-Extra: docx
Requires-Dist: docx ; extra == 'docx'
Provides-Extra: pdf
Requires-Dist: pdfminer.six ; extra == 'pdf'
Provides-Extra: tab
Requires-Dist: pandas ; extra == 'tab'
Provides-Extra: x_option
Requires-Dist: lxml ; extra == 'x_option'
Requires-Dist: cssselect ; extra == 'x_option'
Provides-Extra: xl
Requires-Dist: openpyxl ; extra == 'xl'
Provides-Extra: y_option
Requires-Dist: pyyaml ; extra == 'y_option'
